pyminyus/__init__.py
pyminyus/print_progress.py
pyminyus-0.0.4.dist-info/LICENSE
pyminyus-0.0.4.dist-info/METADATA
pyminyus-0.0.4.dist-info/WHEEL
pyminyus-0.0.4.dist-info/top_level.txt
pyminyus-0.0.4.dist-info/RECORD
